davxmppsync/__init__.py
davxmppsync/__main__.py
davxmppsync/carddav.py
davxmppsync/output.py
davxmppsync/util.py
davxmppsync/validator.py
davxmppsync/xmpp.py
dav_xmpp_sync-1.0.0.dist-info/entry_points.txt
dav_xmpp_sync-1.0.0.dist-info/LICENSE.txt
dav_xmpp_sync-1.0.0.dist-info/WHEEL
dav_xmpp_sync-1.0.0.dist-info/METADATA
dav_xmpp_sync-1.0.0.dist-info/RECORD
