Metadata-Version: 2.1
Name: dav-xmpp-sync
Version: 1.0.0
Summary: Synchronizes contact names from CardDav to XMPP/SMS gateways
License: AGPLv3
Author: Sumit Khanna
Author-email: sumit@penguindreams.org
Requires-Python: >=3.10,<4.0
Classifier: License :: Other/Proprietary License
Classifier: Programming Language :: Python :: 3
Classifier: Programming Language :: Python :: 3.10
Requires-Dist: PyYAML (>=6.0,<7.0)
Requires-Dist: click (>=8.0.3,<9.0.0)
Requires-Dist: requests (>=2.27.1,<3.0.0)
Requires-Dist: rich (>=11.0.0,<12.0.0)
Requires-Dist: xmpppy (>=0.7.0,<0.8.0)
